{"trial_id": "f938d07f1c70c6eb86c8c86e6e44a055", "hyperparameters": {"space": [{"class_name": "Boolean", "config": {"name": "structured_data_block_1/normalize", "default": false, "conditions": []}}, {"class_name": "Boolean", "config": {"name": "structured_data_block_1/dense_block_1/use_batchnorm", "default": false, "conditions": []}}, {"class_name": "Choice", "config": {"name": "structured_data_block_1/dense_block_1/num_layers", "default": 2, "conditions": [], "values": [1, 2, 3], "ordered": true}}, {"class_name": "Choice", "config": {"name": "structured_data_block_1/dense_block_1/units_0", "default": 32, "conditions": [], "values": [16, 32, 64, 128, 256, 512, 1024], "ordered": true}}, {"class_name": "Choice", "config": {"name": "structured_data_block_1/dense_block_1/dropout", "default": 0.0, "conditions": [], "values": [0.0, 0.25, 0.5], "ordered": true}}, {"class_name": "Choice", "config": {"name": "structured_data_block_1/dense_block_1/units_1", "default": 32, "conditions": [], "values": [16, 32, 64, 128, 256, 512, 1024], "ordered": true}}, {"class_name": "Choice", "config": {"name": "classification_head_1/dropout", "default": 0, "conditions": [], "values": [0.0, 0.25, 0.5], "ordered": true}}, {"class_name": "Choice", "config": {"name": "optimizer", "default": "adam", "conditions": [], "values": ["adam", "sgd", "adam_weight_decay"], "ordered": false}}, {"class_name": "Choice", "config": {"name": "learning_rate", "default": 0.001, "conditions": [], "values": [0.1, 0.01, 0.001, 0.0001, 2e-05, 1e-05], "ordered": true}}], "values": {"structured_data_block_1/normalize": true, "structured_data_block_1/dense_block_1/use_batchnorm": false, "structured_data_block_1/dense_block_1/num_layers": 1, "structured_data_block_1/dense_block_1/units_0": 512, "structured_data_block_1/dense_block_1/dropout": 0.0, "structured_data_block_1/dense_block_1/units_1": 1024, "classification_head_1/dropout": 0.0, "optimizer": "adam", "learning_rate": 0.001}}, "metrics": {"metrics": {"loss": {"direction": "min", "observations": [{"value": [0.6032742261886597], "step": 0}, {"value": [0.6094973087310791], "step": 1}, {"value": [0.6123353838920593], "step": 2}, {"value": [0.6336599588394165], "step": 3}, {"value": [0.6256830096244812], "step": 4}, {"value": [0.5912476181983948], "step": 5}, {"value": [0.5930480360984802], "step": 6}, {"value": [0.5553462505340576], "step": 7}, {"value": [0.5311926007270813], "step": 8}, {"value": [0.5130933523178101], "step": 9}, {"value": [0.5112323760986328], "step": 10}, {"value": [0.48600250482559204], "step": 11}, {"value": [0.47843044996261597], "step": 12}, {"value": [0.46237388253211975], "step": 13}, {"value": [0.4558635950088501], "step": 14}, {"value": [0.446748286485672], "step": 15}, {"value": [0.43251314759254456], "step": 16}, {"value": [0.42325559258461], "step": 17}, {"value": [0.41130995750427246], "step": 18}, {"value": [0.40563422441482544], "step": 19}, {"value": [0.396904319524765], "step": 20}, {"value": [0.39975953102111816], "step": 21}, {"value": [0.38465017080307007], "step": 22}, {"value": [0.3888719379901886], "step": 23}, {"value": [0.3844625651836395], "step": 24}]}, "accuracy": {"direction": "max", "observations": [{"value": [0.791015625], "step": 0}, {"value": [0.7750997543334961], "step": 1}, {"value": [0.7760970592498779], "step": 2}, {"value": [0.7557762861251831], "step": 3}, {"value": [0.7487948536872864], "step": 4}, {"value": [0.7586020827293396], "step": 5}, {"value": [0.755236029624939], "step": 6}, {"value": [0.7686170339584351], "step": 7}, {"value": [0.7760555148124695], "step": 8}, {"value": [0.7826629281044006], "step": 9}, {"value": [0.786486029624939], "step": 10}, {"value": [0.7941738963127136], "step": 11}, {"value": [0.7980385422706604], "step": 12}, {"value": [0.8041473031044006], "step": 13}, {"value": [0.807970404624939], "step": 14}, {"value": [0.8119181990623474], "step": 15}, {"value": [0.8173620104789734], "step": 16}, {"value": [0.8216838240623474], "step": 17}, {"value": [0.8258394002914429], "step": 18}, {"value": [0.8277925252914429], "step": 19}, {"value": [0.831823468208313], "step": 20}, {"value": [0.8305767774581909], "step": 21}, {"value": [0.8356466293334961], "step": 22}, {"value": [0.8342337012290955], "step": 23}, {"value": [0.8375997543334961], "step": 24}]}, "val_loss": {"direction": "min", "observations": [{"value": [0.4699769616127014], "step": 0}, {"value": [0.2521969676017761], "step": 1}, {"value": [0.17631496489048004], "step": 2}, {"value": [0.2192058563232422], "step": 3}, {"value": [0.23654520511627197], "step": 4}, {"value": [0.20224659144878387], "step": 5}, {"value": [0.19323985278606415], "step": 6}, {"value": [0.18065668642520905], "step": 7}, {"value": [0.16968853771686554], "step": 8}, {"value": [0.16324152052402496], "step": 9}, {"value": [0.159528911113739], "step": 10}, {"value": [0.1480969488620758], "step": 11}, {"value": [0.14070181548595428], "step": 12}, {"value": [0.1327308565378189], "step": 13}, {"value": [0.12367775291204453], "step": 14}, {"value": [0.12255699932575226], "step": 15}, {"value": [0.11318223178386688], "step": 16}, {"value": [0.10336433351039886], "step": 17}, {"value": [0.09822485595941544], "step": 18}, {"value": [0.09647765010595322], "step": 19}, {"value": [0.08967991173267365], "step": 20}, {"value": [0.08947934210300446], "step": 21}, {"value": [0.08332256972789764], "step": 22}, {"value": [0.08145495504140854], "step": 23}, {"value": [0.08386676758527756], "step": 24}]}, "val_accuracy": {"direction": "max", "observations": [{"value": [1.0], "step": 0}, {"value": [1.0], "step": 1}, {"value": [1.0], "step": 2}, {"value": [1.0], "step": 3}, {"value": [1.0], "step": 4}, {"value": [1.0], "step": 5}, {"value": [1.0], "step": 6}, {"value": [1.0], "step": 7}, {"value": [1.0], "step": 8}, {"value": [1.0], "step": 9}, {"value": [1.0], "step": 10}, {"value": [1.0], "step": 11}, {"value": [1.0], "step": 12}, {"value": [1.0], "step": 13}, {"value": [1.0], "step": 14}, {"value": [1.0], "step": 15}, {"value": [1.0], "step": 16}, {"value": [1.0], "step": 17}, {"value": [1.0], "step": 18}, {"value": [1.0], "step": 19}, {"value": [1.0], "step": 20}, {"value": [1.0], "step": 21}, {"value": [1.0], "step": 22}, {"value": [1.0], "step": 23}, {"value": [1.0], "step": 24}]}}}, "score": 1.0, "best_step": 0, "status": "COMPLETED"}