{"trial_id": "376aaae3177a643ca0a91b4da644a048", "hyperparameters": {"space": [{"class_name": "Choice", "config": {"name": "rnn_block_1/num_layers", "default": 2, "conditions": [], "values": [1, 2, 3], "ordered": true}}, {"class_name": "Boolean", "config": {"name": "dense_block_1/use_batchnorm", "default": false, "conditions": []}}, {"class_name": "Choice", "config": {"name": "dense_block_1/num_layers", "default": 2, "conditions": [], "values": [1, 2, 3], "ordered": true}}, {"class_name": "Choice", "config": {"name": "dense_block_1/units_0", "default": 32, "conditions": [], "values": [16, 32, 64, 128, 256, 512, 1024], "ordered": true}}, {"class_name": "Choice", "config": {"name": "dense_block_1/dropout", "default": 0.0, "conditions": [], "values": [0.0, 0.25, 0.5], "ordered": true}}, {"class_name": "Choice", "config": {"name": "dense_block_1/units_1", "default": 32, "conditions": [], "values": [16, 32, 64, 128, 256, 512, 1024], "ordered": true}}, {"class_name": "Choice", "config": {"name": "classification_head_1/dropout", "default": 0, "conditions": [], "values": [0.0, 0.25, 0.5], "ordered": true}}, {"class_name": "Choice", "config": {"name": "optimizer", "default": "adam", "conditions": [], "values": ["adam", "sgd", "adam_weight_decay"], "ordered": false}}, {"class_name": "Choice", "config": {"name": "learning_rate", "default": 0.001, "conditions": [], "values": [0.1, 0.01, 0.001, 0.0001, 2e-05, 1e-05], "ordered": true}}, {"class_name": "Choice", "config": {"name": "dense_block_1/units_2", "default": 32, "conditions": [], "values": [16, 32, 64, 128, 256, 512, 1024], "ordered": true}}], "values": {"rnn_block_1/num_layers": 2, "dense_block_1/use_batchnorm": false, "dense_block_1/num_layers": 2, "dense_block_1/units_0": 32, "dense_block_1/dropout": 0.25, "dense_block_1/units_1": 1024, "classification_head_1/dropout": 0.25, "optimizer": "adam", "learning_rate": 0.001, "dense_block_1/units_2": 1024}}, "metrics": {"metrics": {"loss": {"direction": "min", "observations": [{"value": [2.3933606147766113], "step": 0}, {"value": [2.2923974990844727], "step": 1}, {"value": [2.38920521736145], "step": 2}, {"value": [2.2574357986450195], "step": 3}, {"value": [2.2739155292510986], "step": 4}, {"value": [2.2367210388183594], "step": 5}, {"value": [2.239553928375244], "step": 6}, {"value": [2.2146449089050293], "step": 7}, {"value": [2.2173750400543213], "step": 8}, {"value": [2.1623754501342773], "step": 9}]}, "accuracy": {"direction": "max", "observations": [{"value": [0.11706840991973877], "step": 0}, {"value": [0.13524200022220612], "step": 1}, {"value": [0.1118878647685051], "step": 2}, {"value": [0.13750475645065308], "step": 3}, {"value": [0.13475371897220612], "step": 4}, {"value": [0.14515052735805511], "step": 5}, {"value": [0.1454363614320755], "step": 6}, {"value": [0.15817931294441223], "step": 7}, {"value": [0.16250237822532654], "step": 8}, {"value": [0.1820991337299347], "step": 9}]}, "val_loss": {"direction": "min", "observations": [{"value": [2.3357770442962646], "step": 0}, {"value": [2.11671781539917], "step": 1}, {"value": [2.2720232009887695], "step": 2}, {"value": [2.08661150932312], "step": 3}, {"value": [2.0831077098846436], "step": 4}, {"value": [2.0549817085266113], "step": 5}, {"value": [2.0123610496520996], "step": 6}, {"value": [1.96809983253479], "step": 7}, {"value": [1.9388978481292725], "step": 8}, {"value": [1.8991323709487915], "step": 9}]}, "val_accuracy": {"direction": "max", "observations": [{"value": [0.0930059552192688], "step": 0}, {"value": [0.0992063507437706], "step": 1}, {"value": [0.1016865074634552], "step": 2}, {"value": [0.0997023805975914], "step": 3}, {"value": [0.1016865074634552], "step": 4}, {"value": [0.1447172611951828], "step": 5}, {"value": [0.2064732164144516], "step": 6}, {"value": [0.251240074634552], "step": 7}, {"value": [0.2601686418056488], "step": 8}, {"value": [0.2848462164402008], "step": 9}]}}}, "score": 1.8991323709487915, "best_step": 9, "status": "COMPLETED"}