{"trial_id": "f15550200c8f917f1f268ceeb7600605", "hyperparameters": {"space": [{"class_name": "Choice", "config": {"name": "rnn_block_1/num_layers", "default": 2, "conditions": [], "values": [1, 2, 3], "ordered": true}}, {"class_name": "Boolean", "config": {"name": "dense_block_1/use_batchnorm", "default": false, "conditions": []}}, {"class_name": "Choice", "config": {"name": "dense_block_1/num_layers", "default": 2, "conditions": [], "values": [1, 2, 3], "ordered": true}}, {"class_name": "Choice", "config": {"name": "dense_block_1/units_0", "default": 32, "conditions": [], "values": [16, 32, 64, 128, 256, 512, 1024], "ordered": true}}, {"class_name": "Choice", "config": {"name": "dense_block_1/dropout", "default": 0.0, "conditions": [], "values": [0.0, 0.25, 0.5], "ordered": true}}, {"class_name": "Choice", "config": {"name": "dense_block_1/units_1", "default": 32, "conditions": [], "values": [16, 32, 64, 128, 256, 512, 1024], "ordered": true}}, {"class_name": "Choice", "config": {"name": "classification_head_1/dropout", "default": 0, "conditions": [], "values": [0.0, 0.25, 0.5], "ordered": true}}, {"class_name": "Choice", "config": {"name": "optimizer", "default": "adam", "conditions": [], "values": ["adam", "sgd", "adam_weight_decay"], "ordered": false}}, {"class_name": "Choice", "config": {"name": "learning_rate", "default": 0.001, "conditions": [], "values": [0.1, 0.01, 0.001, 0.0001, 2e-05, 1e-05], "ordered": true}}], "values": {"rnn_block_1/num_layers": 1, "dense_block_1/use_batchnorm": false, "dense_block_1/num_layers": 1, "dense_block_1/units_0": 32, "dense_block_1/dropout": 0.0, "dense_block_1/units_1": 64, "classification_head_1/dropout": 0.25, "optimizer": "adam", "learning_rate": 0.001}}, "metrics": {"metrics": {"loss": {"direction": "min", "observations": [{"value": [2.3945138454437256], "step": 0}, {"value": [2.3777973651885986], "step": 1}, {"value": [2.3337812423706055], "step": 2}, {"value": [2.282975196838379], "step": 3}, {"value": [2.256403684616089], "step": 4}, {"value": [2.2438840866088867], "step": 5}, {"value": [2.2398791313171387], "step": 6}, {"value": [2.231644868850708], "step": 7}, {"value": [2.2262980937957764], "step": 8}, {"value": [2.2168362140655518], "step": 9}]}, "accuracy": {"direction": "max", "observations": [{"value": [0.11314429342746735], "step": 0}, {"value": [0.12150461971759796], "step": 1}, {"value": [0.13140720129013062], "step": 2}, {"value": [0.13799303770065308], "step": 3}, {"value": [0.14275676012039185], "step": 4}, {"value": [0.14732398092746735], "step": 5}, {"value": [0.14967606961727142], "step": 6}, {"value": [0.15654772520065308], "step": 7}, {"value": [0.1593523770570755], "step": 8}, {"value": [0.1629430204629898], "step": 9}]}, "val_loss": {"direction": "min", "observations": [{"value": [2.379196882247925], "step": 0}, {"value": [2.325716495513916], "step": 1}, {"value": [2.218961238861084], "step": 2}, {"value": [2.1405141353607178], "step": 3}, {"value": [2.0985774993896484], "step": 4}, {"value": [2.0747361183166504], "step": 5}, {"value": [2.060822010040283], "step": 6}, {"value": [2.0498838424682617], "step": 7}, {"value": [2.0381064414978027], "step": 8}, {"value": [2.025113105773926], "step": 9}]}, "val_accuracy": {"direction": "max", "observations": [{"value": [0.1912202388048172], "step": 0}, {"value": [0.1804315447807312], "step": 1}, {"value": [0.1798115074634552], "step": 2}, {"value": [0.1541418582201004], "step": 3}, {"value": [0.1434771865606308], "step": 4}, {"value": [0.1408730149269104], "step": 5}, {"value": [0.144221231341362], "step": 6}, {"value": [0.1524057537317276], "step": 7}, {"value": [0.1638144850730896], "step": 8}, {"value": [0.18514384329319], "step": 9}]}}}, "score": 2.025113105773926, "best_step": 9, "status": "COMPLETED"}